{
  "name": "${project.name}",
  "version": "${project.version}",
  "description": "${project.description}",
  "platform": "complete",
  "dependencies":   [
        {
      "name": "app-platform-complete",
      "version": "^2.1.0"
    },
        {
      "name": "app-fqm",
      "version": "^1.1.0"
    }
  ],
  "modules":   [
        {
      "name": "edge-orders",
      "version": "3.2.2",
      "url": null
    },
        {
      "name": "edge-connexion",
      "version": "1.4.1",
      "url": null
    },
        {
      "name": "edge-dematic",
      "version": "2.4.2",
      "url": null
    },
        {
      "name": "edge-caiasoft",
      "version": "2.4.1",
      "url": null
    },
        {
      "name": "edge-rtac",
      "version": "3.0.0",
      "url": "https://mdr-folio-eis-us-east-1-dev.s3.amazonaws.com/edge-rtac-3.0.0"
    },
        {
      "name": "edge-sip2",
      "version": "3.4.2",
      "url": null
    },
        {
      "name": "edge-fqm",
      "version": "4.0.1",
      "url": null
    },
        {
      "name": "edge-erm",
      "version": "1.4.0",
      "url": null
    },
        {
      "name": "edge-patron",
      "version": "5.3.1",
      "url": null
    },
        {
      "name": "edge-courses",
      "version": "1.6.0",
      "url": null
    },
        {
      "name": "edge-ncip",
      "version": "1.10.2",
      "url": null
    }
  ],
  "uiModules": []
}